MANIFEST.in
README.md
setup.cfg
setup.py
mambas/__init__.py
mambas.egg-info/PKG-INFO
mambas.egg-info/SOURCES.txt
mambas.egg-info/dependency_links.txt
mambas.egg-info/entry_points.txt
mambas.egg-info/requires.txt
mambas.egg-info/top_level.txt
mambas/keras/__init__.py
mambas/keras/callback.py
mambas/server/__init__.py
mambas/server/__main__.py
mambas/server/database.py
mambas/server/models.py
mambas/server/views.py
mambas/server/webserver.py
mambas/server/components/css/custom.css
mambas/server/components/css/material-dashboard.min.css
mambas/server/components/css/plugins/morris.css
mambas/server/components/html/dashboard.tpl.html
mambas/server/components/html/footer.tpl.html
mambas/server/components/html/header.tpl.html
mambas/server/components/html/instructions.tpl.html
mambas/server/components/html/project_dashboard.tpl.html
mambas/server/components/html/project_sessions.tpl.html
mambas/server/components/html/session.tpl.html
mambas/server/components/html/template.html
mambas/server/components/img/cover.jpg
mambas/server/components/img/favicon.ico
mambas/server/components/img/logo.png
mambas/server/components/img/mask.png
mambas/server/components/img/sidebar-1.jpg
mambas/server/components/img/sidebar-2.jpg
mambas/server/components/img/sidebar-3.jpg
mambas/server/components/img/sidebar-4.jpg
mambas/server/components/js/custom.js
mambas/server/components/js/material-dashboard.js
mambas/server/components/js/material-dashboard.min.js
mambas/server/components/js/core/bootstrap-material-design.min.js
mambas/server/components/js/core/jquery.min.js
mambas/server/components/js/core/popper.min.js
mambas/server/components/js/plugins/bootstrap-datetimepicker.min.js
mambas/server/components/js/plugins/bootstrap-notify.js
mambas/server/components/js/plugins/hideshow.min.js
mambas/server/components/js/plugins/jquery.dataTables.min.js
mambas/server/components/js/plugins/moment.min.js
mambas/server/components/js/plugins/morris.min.js
mambas/server/components/js/plugins/perfect-scrollbar.jquery.min.js
mambas/server/components/js/plugins/raphael-min.js
mambas/server/components/js/plugins/sweetalert2.min.js
mambas/server/components/scss/material-dashboard.scss
