Metadata-Version: 1.0
Name: mambas
Version: 0.1.2
Summary: Mambas is a web based visualization tool to manage your Keras projects and monitor your training sessions.
Home-page: https://github.com/misterkevinski/mambas
Author: Kevin Beck
Author-email: misterkevinski@gmail.com
License: MIT
Platform: UNKNOWN
